tensi/__init__.py
tensi/vis.py
tensi-1.0.0.dist-info/licenses/LICENSE
tensi-1.0.0.dist-info/METADATA
tensi-1.0.0.dist-info/WHEEL
tensi-1.0.0.dist-info/top_level.txt
tensi-1.0.0.dist-info/RECORD
