Metadata-Version: 2.4
Name: tensi
Version: 1.0.0
Summary: Interactive tensor shape visualization library
Home-page: https://github.com/DorsaRoh/tensi
Author: Dorsa Rohani
Author-email: dorsa.rohani@gmail.com
Keywords: tensor visualization pytorch numpy plotly deep-learning
Classifier: Development Status :: 4 - Beta
Classifier: Intended Audience :: Developers
Classifier: Intended Audience :: Science/Research
Classifier: Topic :: Scientific/Engineering :: Visualization
Classifier: License :: OSI Approved :: MIT License
Classifier: Programming Language :: Python :: 3
Classifier: Programming Language :: Python :: 3.7
Classifier: Programming Language :: Python :: 3.8
Classifier: Programming Language :: Python :: 3.9
Classifier: Programming Language :: Python :: 3.10
Classifier: Programming Language :: Python :: 3.11
Requires-Python: >=3.7
License-File: LICENSE
Requires-Dist: torch>=1.8.0
Requires-Dist: numpy>=1.19.0
Requires-Dist: plotly>=5.0.0
Dynamic: author
Dynamic: author-email
Dynamic: classifier
Dynamic: description
Dynamic: description-content-type
Dynamic: home-page
Dynamic: keywords
Dynamic: license-file
Dynamic: requires-dist
Dynamic: requires-python
Dynamic: summary
